dhvagna/__init__.py
dhvagna/agents.py
dhvagna/cli.py
dhvagna/utils.py
dhvagna/wav.py
dhvagna-0.1.2.dist-info/LICENSE
dhvagna-0.1.2.dist-info/METADATA
dhvagna-0.1.2.dist-info/WHEEL
dhvagna-0.1.2.dist-info/entry_points.txt
dhvagna-0.1.2.dist-info/top_level.txt
dhvagna-0.1.2.dist-info/RECORD
