Metadata-Version: 2.1
Name: dhvagna
Version: 0.1.2
Summary: A multilingual voice transcription tool for Telugu and English
Home-page: https://github.com/gnanesh-16/Dhwagna
Author: Gnox79
License: UNKNOWN
Platform: UNKNOWN
Classifier: Programming Language :: Python :: 3
Classifier: Programming Language :: Python :: 3.7
Classifier: Programming Language :: Python :: 3.8
Classifier: Programming Language :: Python :: 3.9
Classifier: Programming Language :: Python :: 3.10
Classifier: License :: OSI Approved :: MIT License
Classifier: Operating System :: OS Independent
Classifier: Topic :: Multimedia :: Sound/Audio :: Speech
Classifier: Topic :: Text Processing :: Linguistic
Requires-Python: >=3.7
License-File: LICENSE
Requires-Dist: google-generativeai>=0.3.2
Requires-Dist: SpeechRecognition>=3.10.0
Requires-Dist: keyboard>=0.13.5
Requires-Dist: gTTS>=2.4.0
Requires-Dist: python-dotenv>=1.0.0
Requires-Dist: rich>=13.7.0
Requires-Dist: pathlib>=1.0.1
Requires-Dist: wave>=0.0.2
Requires-Dist: pyaudio>=0.2.14
